daggre/__init__.py
daggre/core/__init__.py
daggre/core/common.py
daggre/core/edge.py
daggre/core/exceptions.py
daggre/core/graph.py
daggre/core/node.py
daggre/static/index.css
daggre/static/index.js
daggre/tests/__init__.py
daggre/tests/conftest.py
daggre/tests/test_core.py
daggre/tests/test_graph_generator_helper.py
daggre/tests/test_transport.py
daggre/transports/__init__.py
daggre/transports/client.py
daggre/transports/connection.py
daggre/transports/exceptions.py
daggre/transports/json.py
daggre/transports/model.py
daggre/transports/server.py
daggre/transports/transport.py
daggre/transports/update.py
daggre/transports/utils.py
daggre/transports/handlers/__init__.py
daggre/transports/handlers/aiohttp_client.py
daggre/transports/handlers/starlette.py
daggre-0.1.1.dist-info/METADATA
daggre-0.1.1.dist-info/WHEEL
daggre-0.1.1.dist-info/licenses/LICENSE
daggre-0.1.1.dist-info/RECORD
