Metadata-Version: 2.3
Name: daggre
Version: 0.1.1
Summary: A convenience layer on top of `dagre-d3` (`dagre-d3-es`).
Project-URL: Repository, https://github.com/timkpaine/daggre
Project-URL: Homepage, https://github.com/timkpaine/daggre
Author-email: Tim Paine <t.paine154@gmail.com>
License:                                  Apache License
License-File: LICENSE
Keywords: DAG,Data,Graph
Classifier: Development Status :: 3 - Alpha
Classifier: License :: OSI Approved :: Apache Software License
Classifier: Programming Language :: Python
Classifier: Programming Language :: Python :: 3
Classifier: Programming Language :: Python :: 3.7
Classifier: Programming Language :: Python :: 3.8
Classifier: Programming Language :: Python :: 3.9
Classifier: Programming Language :: Python :: 3.10
Classifier: Programming Language :: Python :: 3.11
Requires-Python: >=3.7
Requires-Dist: aiohttp
Requires-Dist: aiostream
Requires-Dist: orjson
Requires-Dist: pydantic
Requires-Dist: starlette
Requires-Dist: uvicorn
Requires-Dist: websockets
Provides-Extra: develop
Requires-Dist: black>=23; extra == 'develop'
Requires-Dist: check-manifest; extra == 'develop'
Requires-Dist: isort; extra == 'develop'
Requires-Dist: mypy; extra == 'develop'
Requires-Dist: pytest; extra == 'develop'
Requires-Dist: pytest-cov; extra == 'develop'
Requires-Dist: ruff<0.4,>=0.3; extra == 'develop'
Provides-Extra: test
Requires-Dist: pytest; extra == 'test'
Requires-Dist: pytest-cov; extra == 'test'
